[
    {
        "pick_id": "ee78cb7831c419446aaa1a09513da0e8",
        "match_id": "328644925",
        "fixture_id": "328644925",
        "model_version": "isports_ai77_v1_stats_odds",
        "date": "2026-05-05",
        "time": "14:00",
        "sport": "football",
        "league": "Chinese Super League",
        "league_id": "1066",
        "match": "Chongqing Tonglianglong - Henan Football Club",
        "bet": "Chongqing Tonglianglong",
        "bucket": "home",
        "line": null,
        "odds": 3.0,
        "market_median_odds": 2.49,
        "model_prob": 0.5257,
        "implied_prob": 0.3333,
        "edge": 0.1924,
        "expected_home_goals": 1.51,
        "expected_away_goals": 0.94,
        "expected_total_goals": 2.46,
        "bookmakers_used": 18,
        "confidence": 87.5,
        "quality_score": 89.0,
        "stake": 1.25,
        "stake_label": "Strong",
        "stake_score": 7,
        "result": "pending",
        "reasoning": "Chongqing Tonglianglong is selected as a side-value position in Chinese Super League. The expected goals profile is 1.51 - 0.94. The best price is 3.00, while the market median is around 2.49, creating an estimated value gap of +19.2% across 18 bookmakers."
    },
    {
        "pick_id": "8ba7f526a938236ca33cf253a7da5f7b",
        "match_id": "240017923",
        "fixture_id": "240017923",
        "model_version": "isports_ai77_v1_stats_odds",
        "date": "2026-05-05",
        "time": "14:00",
        "sport": "football",
        "league": "Uzbekistan Second League",
        "league_id": "106118",
        "match": "Respublika FA - FC Lochin",
        "bet": "FC Lochin",
        "bucket": "away",
        "line": null,
        "odds": 3.14,
        "market_median_odds": 3.0,
        "model_prob": 0.5017,
        "implied_prob": 0.3185,
        "edge": 0.1832,
        "expected_home_goals": 0.85,
        "expected_away_goals": 1.44,
        "expected_total_goals": 2.29,
        "bookmakers_used": 9,
        "confidence": 82.0,
        "quality_score": 83.2,
        "stake": 1.25,
        "stake_label": "Strong",
        "stake_score": 6,
        "result": "pending",
        "reasoning": "FC Lochin is selected as a side-value position in Uzbekistan Second League. The expected goals profile is 0.85 - 1.44. The best price is 3.14, while the market median is around 3.00, creating an estimated value gap of +18.3% across 9 bookmakers."
    },
    {
        "pick_id": "ddd1b2c8eb8408a7fcdbd5346aceb940",
        "match_id": "356714924",
        "fixture_id": "356714924",
        "model_version": "isports_ai77_v1_stats_odds",
        "date": "2026-05-05",
        "time": "16:00",
        "sport": "football",
        "league": "Indian Super League",
        "league_id": "176317",
        "match": "Mumbai City - East Bengal",
        "bet": "East Bengal",
        "bucket": "away",
        "line": null,
        "odds": 2.45,
        "market_median_odds": 2.35,
        "model_prob": 0.5355,
        "implied_prob": 0.4082,
        "edge": 0.1273,
        "expected_home_goals": 1.06,
        "expected_away_goals": 1.82,
        "expected_total_goals": 2.88,
        "bookmakers_used": 18,
        "confidence": 89.6,
        "quality_score": 89.5,
        "stake": 1.25,
        "stake_label": "Strong",
        "stake_score": 7,
        "result": "pending",
        "reasoning": "East Bengal is selected as a side-value position in Indian Super League. The expected goals profile is 1.06 - 1.82. The best price is 2.45, while the market median is around 2.35, creating an estimated value gap of +12.7% across 18 bookmakers."
    },
    {
        "pick_id": "89fb334b9a3ba3f478997fb64acb5f72",
        "match_id": "201018921",
        "fixture_id": "201018921",
        "model_version": "isports_ai77_v1_stats_odds",
        "date": "2026-05-05",
        "time": "18:00",
        "sport": "football",
        "league": "Bahraini Premier League",
        "league_id": "18132",
        "match": "Al-Riffa - Al-Shabbab",
        "bet": "Under 2.5",
        "bucket": "under_2_5",
        "line": 2.5,
        "odds": 2.0,
        "market_median_odds": 1.9,
        "model_prob": 0.6203,
        "implied_prob": 0.5,
        "edge": 0.1203,
        "expected_home_goals": 1.58,
        "expected_away_goals": 0.63,
        "expected_total_goals": 2.21,
        "bookmakers_used": 10,
        "confidence": 91.9,
        "quality_score": 81.9,
        "stake": 1.25,
        "stake_label": "Strong",
        "stake_score": 6,
        "result": "pending",
        "reasoning": "Al-Riffa - Al-Shabbab projects as a more controlled scoring environment. The model total is 2.21, with recent form and league tempo not fully supporting a high-event game. The best available price is 2.00 versus a market median near 1.90, leaving an estimated value gap of +12.0% across 10 bookmakers."
    },
    {
        "pick_id": "1ae6ed13f9432cb66b35b081ef31189b",
        "match_id": "223274929",
        "fixture_id": "223274929",
        "model_version": "isports_ai77_v1_stats_odds",
        "date": "2026-05-05",
        "time": "19:00",
        "sport": "football",
        "league": "TOPLYGA",
        "league_id": "17120",
        "match": "FK Riteriai - FK Banga Gargzdai",
        "bet": "Under 2.5",
        "bucket": "under_2_5",
        "line": 2.5,
        "odds": 2.0,
        "market_median_odds": 1.83,
        "model_prob": 0.6614,
        "implied_prob": 0.5,
        "edge": 0.1614,
        "expected_home_goals": 0.48,
        "expected_away_goals": 1.58,
        "expected_total_goals": 2.06,
        "bookmakers_used": 15,
        "confidence": 92,
        "quality_score": 88.5,
        "stake": 1.5,
        "stake_label": "Top Rated",
        "stake_score": 8,
        "result": "pending",
        "reasoning": "FK Riteriai - FK Banga Gargzdai projects as a more controlled scoring environment. The model total is 2.06, with recent form and league tempo not fully supporting a high-event game. The best available price is 2.00 versus a market median near 1.83, leaving an estimated value gap of +16.1% across 15 bookmakers."
    }
]
