[
    {
        "matchId": "368393829",
        "leagueType": 2,
        "leagueId": "29650",
        "leagueName": "FYR Macedonia Cup",
        "leagueShortName": "MKD CUP",
        "leagueColor": "#cc9900",
        "subLeagueId": "",
        "subLeagueName": "",
        "matchTime": 1756216800,
        "halfStartTime": 0,
        "status": -1,
        "homeId": "75173",
        "homeName": "Bashkimi 2008",
        "awayId": "63039",
        "awayName": "Detonit Plachkovica",
        "homeScore": 1,
        "awayScore": 4,
        "homeHalfScore": 1,
        "awayHalfScore": 2,
        "homeRed": 0,
        "awayRed": 0,
        "homeYellow": 0,
        "awayYellow": 0,
        "homeCorner": 0,
        "awayCorner": 0,
        "homeRank": "",
        "awayRank": "MKD D2-5",
        "season": "2025-2026",
        "stageId": "26990",
        "round": "Round 1",
        "group": "",
        "location": "",
        "weather": "",
        "temperature": "",
        "explain": "",
        "extraExplain": {
            "kickOff": 0,
            "minute": 0,
            "homeScore": 0,
            "awayScore": 0,
            "extraTimeStatus": 0,
            "extraHomeScore": 0,
            "extraAwayScore": 0,
            "penHomeScore": 0,
            "penAwayScore": 0,
            "twoRoundsHomeScore": 0,
            "twoRoundsAwayScore": 0,
            "winner": 0
        },
        "hasLineup": false,
        "neutral": false,
        "injuryTime": 0,
        "var": "",
        "updateTime": 1756228398
    },
    {
        "matchId": "488393821",
        "leagueType": 2,
        "leagueId": "29650",
        "leagueName": "FYR Macedonia Cup",
        "leagueShortName": "MKD CUP",
        "leagueColor": "#cc9900",
        "subLeagueId": "",
        "subLeagueName": "",
        "matchTime": 1756216800,
        "halfStartTime": 1756216800,
        "status": -1,
        "homeId": "75174",
        "homeName": "Evrotip Online",
        "awayId": "2383",
        "awayName": "Sileks",
        "homeScore": 1,
        "awayScore": 7,
        "homeHalfScore": 0,
        "awayHalfScore": 1,
        "homeRed": 0,
        "awayRed": 0,
        "homeYellow": 0,
        "awayYellow": 0,
        "homeCorner": 0,
        "awayCorner": 0,
        "homeRank": "",
        "awayRank": "MKD D1-1",
        "season": "2025-2026",
        "stageId": "26990",
        "round": "Round 1",
        "group": "",
        "location": "",
        "weather": "",
        "temperature": "",
        "explain": "",
        "extraExplain": {
            "kickOff": 0,
            "minute": 0,
            "homeScore": 0,
            "awayScore": 0,
            "extraTimeStatus": 0,
            "extraHomeScore": 0,
            "extraAwayScore": 0,
            "penHomeScore": 0,
            "penAwayScore": 0,
            "twoRoundsHomeScore": 0,
            "twoRoundsAwayScore": 0,
            "winner": 0
        },
        "hasLineup": false,
        "neutral": false,
        "injuryTime": 0,
        "var": "",
        "updateTime": 1756225465
    },
    {
        "matchId": "339393827",
        "leagueType": 2,
        "leagueId": "29650",
        "leagueName": "FYR Macedonia Cup",
        "leagueShortName": "MKD CUP",
        "leagueColor": "#cc9900",
        "subLeagueId": "",
        "subLeagueName": "",
        "matchTime": 1756216800,
        "halfStartTime": 1756216800,
        "status": -1,
        "homeId": "17693",
        "homeName": "Ljuboten",
        "awayId": "4396",
        "awayName": "FK Makedonija Gjorce Petrov",
        "homeScore": 0,
        "awayScore": 14,
        "homeHalfScore": 0,
        "awayHalfScore": 7,
        "homeRed": 0,
        "awayRed": 0,
        "homeYellow": 0,
        "awayYellow": 0,
        "homeCorner": 0,
        "awayCorner": 0,
        "homeRank": "",
        "awayRank": "MKD D1-11",
        "season": "2025-2026",
        "stageId": "26990",
        "round": "Round 1",
        "group": "",
        "location": "",
        "weather": "",
        "temperature": "",
        "explain": "",
        "extraExplain": {
            "kickOff": 0,
            "minute": 0,
            "homeScore": 0,
            "awayScore": 0,
            "extraTimeStatus": 0,
            "extraHomeScore": 0,
            "extraAwayScore": 0,
            "penHomeScore": 0,
            "penAwayScore": 0,
            "twoRoundsHomeScore": 0,
            "twoRoundsAwayScore": 0,
            "winner": 0
        },
        "hasLineup": false,
        "neutral": false,
        "injuryTime": 0,
        "var": "",
        "updateTime": 1756227386
    },
    {
        "matchId": "349393828",
        "leagueType": 2,
        "leagueId": "29650",
        "leagueName": "FYR Macedonia Cup",
        "leagueShortName": "MKD CUP",
        "leagueColor": "#cc9900",
        "subLeagueId": "",
        "subLeagueName": "",
        "matchTime": 1756216800,
        "halfStartTime": 1756220658,
        "status": -1,
        "homeId": "15340",
        "homeName": "FK Ohrid 2004",
        "awayId": "26821",
        "awayName": "Academy Pandev",
        "homeScore": 1,
        "awayScore": 1,
        "homeHalfScore": 0,
        "awayHalfScore": 1,
        "homeRed": 1,
        "awayRed": 0,
        "homeYellow": 3,
        "awayYellow": 2,
        "homeCorner": 1,
        "awayCorner": 4,
        "homeRank": "MKD D2-7",
        "awayRank": "MKD D1-10",
        "season": "2025-2026",
        "stageId": "26990",
        "round": "Round 1",
        "group": "",
        "location": "",
        "weather": "Few Cloudy",
        "temperature": "25°C",
        "explain": "",
        "extraExplain": {
            "kickOff": 0,
            "minute": 90,
            "homeScore": 1,
            "awayScore": 1,
            "extraTimeStatus": 0,
            "extraHomeScore": 0,
            "extraAwayScore": 0,
            "penHomeScore": 5,
            "penAwayScore": 3,
            "twoRoundsHomeScore": 0,
            "twoRoundsAwayScore": 0,
            "winner": 1
        },
        "hasLineup": false,
        "neutral": false,
        "injuryTime": 0,
        "var": "",
        "updateTime": 1756252819
    },
    {
        "matchId": "479393821",
        "leagueType": 2,
        "leagueId": "29650",
        "leagueName": "FYR Macedonia Cup",
        "leagueShortName": "MKD CUP",
        "leagueColor": "#cc9900",
        "subLeagueId": "",
        "subLeagueName": "",
        "matchTime": 1756216800,
        "halfStartTime": 1756220713,
        "status": -1,
        "homeId": "34636",
        "homeName": "Pobeda Valandovo",
        "awayId": "4824",
        "awayName": "Bregalnica Stip",
        "homeScore": 0,
        "awayScore": 6,
        "homeHalfScore": 0,
        "awayHalfScore": 2,
        "homeRed": 0,
        "awayRed": 0,
        "homeYellow": 0,
        "awayYellow": 0,
        "homeCorner": 0,
        "awayCorner": 0,
        "homeRank": "",
        "awayRank": "MKD D2-4",
        "season": "2025-2026",
        "stageId": "26990",
        "round": "Round 1",
        "group": "",
        "location": "",
        "weather": "",
        "temperature": "",
        "explain": "",
        "extraExplain": {
            "kickOff": 0,
            "minute": 0,
            "homeScore": 0,
            "awayScore": 0,
            "extraTimeStatus": 0,
            "extraHomeScore": 0,
            "extraAwayScore": 0,
            "penHomeScore": 0,
            "penAwayScore": 0,
            "twoRoundsHomeScore": 0,
            "twoRoundsAwayScore": 0,
            "winner": 0
        },
        "hasLineup": false,
        "neutral": false,
        "injuryTime": 0,
        "var": "",
        "updateTime": 1756223435
    },
    {
        "matchId": "319393825",
        "leagueType": 2,
        "leagueId": "29650",
        "leagueName": "FYR Macedonia Cup",
        "leagueShortName": "MKD CUP",
        "leagueColor": "#cc9900",
        "subLeagueId": "",
        "subLeagueName": "",
        "matchTime": 1756216800,
        "halfStartTime": 1756220374,
        "status": -1,
        "homeId": "15346",
        "homeName": "Karbinci",
        "awayId": "2557",
        "awayName": "Rabotnicki Skopje",
        "homeScore": 0,
        "awayScore": 16,
        "homeHalfScore": 0,
        "awayHalfScore": 9,
        "homeRed": 0,
        "awayRed": 0,
        "homeYellow": 0,
        "awayYellow": 0,
        "homeCorner": 0,
        "awayCorner": 0,
        "homeRank": "",
        "awayRank": "MKD D1-9",
        "season": "2025-2026",
        "stageId": "26990",
        "round": "Round 1",
        "group": "",
        "location": "",
        "weather": "",
        "temperature": "",
        "explain": "",
        "extraExplain": {
            "kickOff": 0,
            "minute": 0,
            "homeScore": 0,
            "awayScore": 0,
            "extraTimeStatus": 0,
            "extraHomeScore": 0,
            "extraAwayScore": 0,
            "penHomeScore": 0,
            "penAwayScore": 0,
            "twoRoundsHomeScore": 0,
            "twoRoundsAwayScore": 0,
            "winner": 0
        },
        "hasLineup": false,
        "neutral": false,
        "injuryTime": 0,
        "var": "",
        "updateTime": 1756223116
    },
    {
        "matchId": "478393820",
        "leagueType": 2,
        "leagueId": "29650",
        "leagueName": "FYR Macedonia Cup",
        "leagueShortName": "MKD CUP",
        "leagueColor": "#cc9900",
        "subLeagueId": "",
        "subLeagueName": "",
        "matchTime": 1756305000,
        "halfStartTime": 1756308900,
        "status": -1,
        "homeId": "697",
        "homeName": "Belasica Strumica",
        "awayId": "63040",
        "awayName": "KF Arsimi",
        "homeScore": 2,
        "awayScore": 2,
        "homeHalfScore": 0,
        "awayHalfScore": 1,
        "homeRed": 0,
        "awayRed": 1,
        "homeYellow": 2,
        "awayYellow": 1,
        "homeCorner": 6,
        "awayCorner": 4,
        "homeRank": "MKD D2-8",
        "awayRank": "MKD D1-7",
        "season": "2025-2026",
        "stageId": "26990",
        "round": "Round 1",
        "group": "",
        "location": "Mladost Stadium",
        "weather": "Clear",
        "temperature": "32°C",
        "explain": "",
        "extraExplain": {
            "kickOff": 0,
            "minute": 90,
            "homeScore": 2,
            "awayScore": 2,
            "extraTimeStatus": 0,
            "extraHomeScore": 0,
            "extraAwayScore": 0,
            "penHomeScore": 3,
            "penAwayScore": 2,
            "twoRoundsHomeScore": 0,
            "twoRoundsAwayScore": 0,
            "winner": 1
        },
        "hasLineup": false,
        "neutral": false,
        "injuryTime": 0,
        "var": "",
        "updateTime": 1756312669
    },
    {
        "matchId": "489393822",
        "leagueType": 2,
        "leagueId": "29650",
        "leagueName": "FYR Macedonia Cup",
        "leagueShortName": "MKD CUP",
        "leagueColor": "#cc9900",
        "subLeagueId": "",
        "subLeagueName": "",
        "matchTime": 1756819800,
        "halfStartTime": 1756824095,
        "status": -1,
        "homeId": "71510",
        "homeName": "Shkendija Haracine",
        "awayId": "15347",
        "awayName": "Kamenica-Sasa",
        "homeScore": 1,
        "awayScore": 1,
        "homeHalfScore": 0,
        "awayHalfScore": 0,
        "homeRed": 1,
        "awayRed": 0,
        "homeYellow": 4,
        "awayYellow": 1,
        "homeCorner": 10,
        "awayCorner": 3,
        "homeRank": "MKD D2-1",
        "awayRank": "MKD D2-12",
        "season": "2025-2026",
        "stageId": "26990",
        "round": "Round 1",
        "group": "",
        "location": "",
        "weather": "Few Cloudy",
        "temperature": "32°C",
        "explain": "",
        "extraExplain": {
            "kickOff": 0,
            "minute": 90,
            "homeScore": 1,
            "awayScore": 1,
            "extraTimeStatus": 0,
            "extraHomeScore": 0,
            "extraAwayScore": 0,
            "penHomeScore": 4,
            "penAwayScore": 3,
            "twoRoundsHomeScore": 0,
            "twoRoundsAwayScore": 0,
            "winner": 1
        },
        "hasLineup": false,
        "neutral": false,
        "injuryTime": 0,
        "var": "",
        "updateTime": 1756857609
    },
    {
        "matchId": "499393823",
        "leagueType": 2,
        "leagueId": "29650",
        "leagueName": "FYR Macedonia Cup",
        "leagueShortName": "MKD CUP",
        "leagueColor": "#cc9900",
        "subLeagueId": "",
        "subLeagueName": "",
        "matchTime": 1756906200,
        "halfStartTime": 1756910181,
        "status": -1,
        "homeId": "10929",
        "homeName": "FK Teteks Tetovo",
        "awayId": "4828",
        "awayName": "Pelister Bitola",
        "homeScore": 1,
        "awayScore": 2,
        "homeHalfScore": 1,
        "awayHalfScore": 0,
        "homeRed": 0,
        "awayRed": 0,
        "homeYellow": 6,
        "awayYellow": 2,
        "homeCorner": 1,
        "awayCorner": 8,
        "homeRank": "MKD D2-8",
        "awayRank": "MKD D1-6",
        "season": "2025-2026",
        "stageId": "26990",
        "round": "Round 1",
        "group": "",
        "location": "",
        "weather": "Cloudy",
        "temperature": "21°C",
        "explain": "",
        "extraExplain": {
            "kickOff": 0,
            "minute": 0,
            "homeScore": 0,
            "awayScore": 0,
            "extraTimeStatus": 0,
            "extraHomeScore": 0,
            "extraAwayScore": 0,
            "penHomeScore": 0,
            "penAwayScore": 0,
            "twoRoundsHomeScore": 0,
            "twoRoundsAwayScore": 0,
            "winner": 0
        },
        "hasLineup": false,
        "neutral": false,
        "injuryTime": 0,
        "var": "",
        "updateTime": 1756944008
    },
    {
        "matchId": "359393829",
        "leagueType": 2,
        "leagueId": "29650",
        "leagueName": "FYR Macedonia Cup",
        "leagueShortName": "MKD CUP",
        "leagueColor": "#cc9900",
        "subLeagueId": "",
        "subLeagueName": "",
        "matchTime": 1756906800,
        "halfStartTime": 1756911281,
        "status": -1,
        "homeId": "75175",
        "homeName": "Pcinja",
        "awayId": "15349",
        "awayName": "FK Novaci",
        "homeScore": 0,
        "awayScore": 3,
        "homeHalfScore": 0,
        "awayHalfScore": 1,
        "homeRed": 0,
        "awayRed": 0,
        "homeYellow": 0,
        "awayYellow": 0,
        "homeCorner": 0,
        "awayCorner": 0,
        "homeRank": "",
        "awayRank": "MKD D2-10",
        "season": "2025-2026",
        "stageId": "26990",
        "round": "Round 1",
        "group": "",
        "location": "",
        "weather": "",
        "temperature": "",
        "explain": "",
        "extraExplain": {
            "kickOff": 0,
            "minute": 0,
            "homeScore": 0,
            "awayScore": 0,
            "extraTimeStatus": 0,
            "extraHomeScore": 0,
            "extraAwayScore": 0,
            "penHomeScore": 0,
            "penAwayScore": 0,
            "twoRoundsHomeScore": 0,
            "twoRoundsAwayScore": 0,
            "winner": 0
        },
        "hasLineup": false,
        "neutral": false,
        "injuryTime": 0,
        "var": "",
        "updateTime": 1756914152
    },
    {
        "matchId": "469393820",
        "leagueType": 2,
        "leagueId": "29650",
        "leagueName": "FYR Macedonia Cup",
        "leagueShortName": "MKD CUP",
        "leagueColor": "#cc9900",
        "subLeagueId": "",
        "subLeagueName": "",
        "matchTime": 1757425200,
        "halfStartTime": 1757429308,
        "status": -1,
        "homeId": "2391",
        "homeName": "Pobeda Prilep",
        "awayId": "20356",
        "awayName": "FK Bashkimi",
        "homeScore": 0,
        "awayScore": 4,
        "homeHalfScore": 0,
        "awayHalfScore": 1,
        "homeRed": 0,
        "awayRed": 0,
        "homeYellow": 0,
        "awayYellow": 0,
        "homeCorner": 2,
        "awayCorner": 2,
        "homeRank": "MKD D2-15",
        "awayRank": "MKD D1-5",
        "season": "2025-2026",
        "stageId": "26990",
        "round": "Round 1",
        "group": "",
        "location": "Goce Delchev - Prilep",
        "weather": "Clear",
        "temperature": "30°C",
        "explain": "",
        "extraExplain": {
            "kickOff": 0,
            "minute": 0,
            "homeScore": 0,
            "awayScore": 0,
            "extraTimeStatus": 0,
            "extraHomeScore": 0,
            "extraAwayScore": 0,
            "penHomeScore": 0,
            "penAwayScore": 0,
            "twoRoundsHomeScore": 0,
            "twoRoundsAwayScore": 0,
            "winner": 0
        },
        "hasLineup": false,
        "neutral": false,
        "injuryTime": 0,
        "var": "",
        "updateTime": 1757432286
    },
    {
        "matchId": "498393822",
        "leagueType": 2,
        "leagueId": "29650",
        "leagueName": "FYR Macedonia Cup",
        "leagueShortName": "MKD CUP",
        "leagueColor": "#cc9900",
        "subLeagueId": "",
        "subLeagueName": "",
        "matchTime": 1757511000,
        "halfStartTime": 1757514835,
        "status": -1,
        "homeId": "11764",
        "homeName": "FK Skopje",
        "awayId": "15344",
        "awayName": "FK Tikves Kavadarci",
        "homeScore": 0,
        "awayScore": 1,
        "homeHalfScore": 0,
        "awayHalfScore": 0,
        "homeRed": 0,
        "awayRed": 0,
        "homeYellow": 0,
        "awayYellow": 3,
        "homeCorner": 4,
        "awayCorner": 5,
        "homeRank": "MKD D2-8",
        "awayRank": "MKD D1-9",
        "season": "2025-2026",
        "stageId": "26990",
        "round": "Round 1",
        "group": "",
        "location": "",
        "weather": "Few Cloudy",
        "temperature": "32°C",
        "explain": "",
        "extraExplain": {
            "kickOff": 0,
            "minute": 0,
            "homeScore": 0,
            "awayScore": 0,
            "extraTimeStatus": 0,
            "extraHomeScore": 0,
            "extraAwayScore": 0,
            "penHomeScore": 0,
            "penAwayScore": 0,
            "twoRoundsHomeScore": 0,
            "twoRoundsAwayScore": 0,
            "winner": 0
        },
        "hasLineup": false,
        "neutral": false,
        "injuryTime": 0,
        "var": "",
        "updateTime": 1757548835
    },
    {
        "matchId": "309393824",
        "leagueType": 2,
        "leagueId": "29650",
        "leagueName": "FYR Macedonia Cup",
        "leagueShortName": "MKD CUP",
        "leagueColor": "#cc9900",
        "subLeagueId": "",
        "subLeagueName": "",
        "matchTime": 1757511000,
        "halfStartTime": 1757515118,
        "status": -1,
        "homeId": "71509",
        "homeName": "Jenimaale Bitola",
        "awayId": "4827",
        "awayName": "FK Shkendija 79",
        "homeScore": 0,
        "awayScore": 9,
        "homeHalfScore": 0,
        "awayHalfScore": 5,
        "homeRed": 0,
        "awayRed": 0,
        "homeYellow": 0,
        "awayYellow": 0,
        "homeCorner": 0,
        "awayCorner": 0,
        "homeRank": "",
        "awayRank": "MKD D1-4",
        "season": "2025-2026",
        "stageId": "26990",
        "round": "Round 1",
        "group": "",
        "location": "",
        "weather": "Cloudy",
        "temperature": "29°C",
        "explain": "",
        "extraExplain": {
            "kickOff": 0,
            "minute": 0,
            "homeScore": 0,
            "awayScore": 0,
            "extraTimeStatus": 0,
            "extraHomeScore": 0,
            "extraAwayScore": 0,
            "penHomeScore": 0,
            "penAwayScore": 0,
            "twoRoundsHomeScore": 0,
            "twoRoundsAwayScore": 0,
            "winner": 0
        },
        "hasLineup": false,
        "neutral": false,
        "injuryTime": 0,
        "var": "",
        "updateTime": 1757548835
    },
    {
        "matchId": "329393826",
        "leagueType": 2,
        "leagueId": "29650",
        "leagueName": "FYR Macedonia Cup",
        "leagueShortName": "MKD CUP",
        "leagueColor": "#cc9900",
        "subLeagueId": "",
        "subLeagueName": "",
        "matchTime": 1757511000,
        "halfStartTime": 1757514858,
        "status": -1,
        "homeId": "23427",
        "homeName": "FK Kozuv",
        "awayId": "21154",
        "awayName": "FK Shkupi",
        "homeScore": 0,
        "awayScore": 2,
        "homeHalfScore": 0,
        "awayHalfScore": 1,
        "homeRed": 0,
        "awayRed": 1,
        "homeYellow": 2,
        "awayYellow": 1,
        "homeCorner": 5,
        "awayCorner": 5,
        "homeRank": "MKD D2-4",
        "awayRank": "MKD D1-12",
        "season": "2025-2026",
        "stageId": "26990",
        "round": "Round 1",
        "group": "",
        "location": "",
        "weather": "Few Cloudy",
        "temperature": "30°C",
        "explain": "",
        "extraExplain": {
            "kickOff": 0,
            "minute": 0,
            "homeScore": 0,
            "awayScore": 0,
            "extraTimeStatus": 0,
            "extraHomeScore": 0,
            "extraAwayScore": 0,
            "penHomeScore": 0,
            "penAwayScore": 0,
            "twoRoundsHomeScore": 0,
            "twoRoundsAwayScore": 0,
            "winner": 0
        },
        "hasLineup": false,
        "neutral": false,
        "injuryTime": 0,
        "var": "",
        "updateTime": 1757548835
    },
    {
        "matchId": "308067821",
        "leagueType": 2,
        "leagueId": "29650",
        "leagueName": "FYR Macedonia Cup",
        "leagueShortName": "MKD CUP",
        "leagueColor": "#cc9900",
        "subLeagueId": "",
        "subLeagueName": "",
        "matchTime": 1758718800,
        "halfStartTime": 1758722700,
        "status": -1,
        "homeId": "697",
        "homeName": "Belasica Strumica",
        "awayId": "63039",
        "awayName": "Detonit Plachkovica",
        "homeScore": 0,
        "awayScore": 1,
        "homeHalfScore": 0,
        "awayHalfScore": 1,
        "homeRed": 0,
        "awayRed": 0,
        "homeYellow": 2,
        "awayYellow": 0,
        "homeCorner": 6,
        "awayCorner": 2,
        "homeRank": "MKD D2-2",
        "awayRank": "MKD D2-8",
        "season": "2025-2026",
        "stageId": "27276",
        "round": "Round 2",
        "group": "",
        "location": "Mladost Stadium",
        "weather": "Few Cloudy",
        "temperature": "30°C",
        "explain": "",
        "extraExplain": {
            "kickOff": 0,
            "minute": 0,
            "homeScore": 0,
            "awayScore": 0,
            "extraTimeStatus": 0,
            "extraHomeScore": 0,
            "extraAwayScore": 0,
            "penHomeScore": 0,
            "penAwayScore": 0,
            "twoRoundsHomeScore": 0,
            "twoRoundsAwayScore": 0,
            "winner": 0
        },
        "hasLineup": false,
        "neutral": false,
        "injuryTime": 0,
        "var": "",
        "updateTime": 1758758416
    },
    {
        "matchId": "328067823",
        "leagueType": 2,
        "leagueId": "29650",
        "leagueName": "FYR Macedonia Cup",
        "leagueShortName": "MKD CUP",
        "leagueColor": "#cc9900",
        "subLeagueId": "",
        "subLeagueName": "",
        "matchTime": 1758718800,
        "halfStartTime": 1758722641,
        "status": -1,
        "homeId": "15340",
        "homeName": "FK Ohrid 2004",
        "awayId": "21154",
        "awayName": "FK Shkupi",
        "homeScore": 3,
        "awayScore": 0,
        "homeHalfScore": 2,
        "awayHalfScore": 0,
        "homeRed": 0,
        "awayRed": 0,
        "homeYellow": 2,
        "awayYellow": 4,
        "homeCorner": 5,
        "awayCorner": 4,
        "homeRank": "MKD D2-7",
        "awayRank": "MKD D1-12",
        "season": "2025-2026",
        "stageId": "27276",
        "round": "Round 2",
        "group": "",
        "location": "",
        "weather": "Few Cloudy",
        "temperature": "26°C",
        "explain": "",
        "extraExplain": {
            "kickOff": 0,
            "minute": 0,
            "homeScore": 0,
            "awayScore": 0,
            "extraTimeStatus": 0,
            "extraHomeScore": 0,
            "extraAwayScore": 0,
            "penHomeScore": 0,
            "penAwayScore": 0,
            "twoRoundsHomeScore": 0,
            "twoRoundsAwayScore": 0,
            "winner": 0
        },
        "hasLineup": false,
        "neutral": false,
        "injuryTime": 0,
        "var": "",
        "updateTime": 1758758416
    },
    {
        "matchId": "338067824",
        "leagueType": 2,
        "leagueId": "29650",
        "leagueName": "FYR Macedonia Cup",
        "leagueShortName": "MKD CUP",
        "leagueColor": "#cc9900",
        "subLeagueId": "",
        "subLeagueName": "",
        "matchTime": 1761048000,
        "halfStartTime": 1761051647,
        "status": -1,
        "homeId": "2557",
        "homeName": "Rabotnicki Skopje",
        "awayId": "4824",
        "awayName": "Bregalnica Stip",
        "homeScore": 1,
        "awayScore": 1,
        "homeHalfScore": 1,
        "awayHalfScore": 0,
        "homeRed": 0,
        "awayRed": 0,
        "homeYellow": 2,
        "awayYellow": 2,
        "homeCorner": 6,
        "awayCorner": 1,
        "homeRank": "MKD D1-11",
        "awayRank": "MKD D2-1",
        "season": "2025-2026",
        "stageId": "27276",
        "round": "Round 2",
        "group": "",
        "location": "Gradski vrt",
        "weather": "Cloudy",
        "temperature": "18°C",
        "explain": "",
        "extraExplain": {
            "kickOff": 0,
            "minute": 90,
            "homeScore": 1,
            "awayScore": 1,
            "extraTimeStatus": 0,
            "extraHomeScore": 0,
            "extraAwayScore": 0,
            "penHomeScore": 4,
            "penAwayScore": 3,
            "twoRoundsHomeScore": 0,
            "twoRoundsAwayScore": 0,
            "winner": 1
        },
        "hasLineup": false,
        "neutral": false,
        "injuryTime": 0,
        "var": "",
        "updateTime": 1761055232
    },
    {
        "matchId": "348067825",
        "leagueType": 2,
        "leagueId": "29650",
        "leagueName": "FYR Macedonia Cup",
        "leagueShortName": "MKD CUP",
        "leagueColor": "#cc9900",
        "subLeagueId": "",
        "subLeagueName": "",
        "matchTime": 1761048000,
        "halfStartTime": 1761051903,
        "status": -1,
        "homeId": "71510",
        "homeName": "Shkendija Haracine",
        "awayId": "4828",
        "awayName": "Pelister Bitola",
        "homeScore": 1,
        "awayScore": 0,
        "homeHalfScore": 0,
        "awayHalfScore": 0,
        "homeRed": 0,
        "awayRed": 0,
        "homeYellow": 1,
        "awayYellow": 0,
        "homeCorner": 4,
        "awayCorner": 5,
        "homeRank": "MKD D2-2",
        "awayRank": "MKD D1-10",
        "season": "2025-2026",
        "stageId": "27276",
        "round": "Round 2",
        "group": "",
        "location": "",
        "weather": "Cloudy",
        "temperature": "18°C",
        "explain": "",
        "extraExplain": {
            "kickOff": 0,
            "minute": 0,
            "homeScore": 0,
            "awayScore": 0,
            "extraTimeStatus": 0,
            "extraHomeScore": 0,
            "extraAwayScore": 0,
            "penHomeScore": 0,
            "penAwayScore": 0,
            "twoRoundsHomeScore": 0,
            "twoRoundsAwayScore": 0,
            "winner": 0
        },
        "hasLineup": false,
        "neutral": false,
        "injuryTime": 0,
        "var": "",
        "updateTime": 1761054652
    },
    {
        "matchId": "318067822",
        "leagueType": 2,
        "leagueId": "29650",
        "leagueName": "FYR Macedonia Cup",
        "leagueShortName": "MKD CUP",
        "leagueColor": "#cc9900",
        "subLeagueId": "",
        "subLeagueName": "",
        "matchTime": 1761048000,
        "halfStartTime": 1761051595,
        "status": -1,
        "homeId": "4396",
        "homeName": "FK Makedonija Gjorce Petrov",
        "awayId": "33778",
        "awayName": "FC Struga Trim Lum",
        "homeScore": 0,
        "awayScore": 5,
        "homeHalfScore": 0,
        "awayHalfScore": 1,
        "homeRed": 0,
        "awayRed": 0,
        "homeYellow": 2,
        "awayYellow": 1,
        "homeCorner": 6,
        "awayCorner": 4,
        "homeRank": "MKD D1-6",
        "awayRank": "MKD D1-1",
        "season": "2025-2026",
        "stageId": "27276",
        "round": "Round 2",
        "group": "",
        "location": "Gjorche Petrov",
        "weather": "Cloudy",
        "temperature": "18°C",
        "explain": "",
        "extraExplain": {
            "kickOff": 0,
            "minute": 0,
            "homeScore": 0,
            "awayScore": 0,
            "extraTimeStatus": 0,
            "extraHomeScore": 0,
            "extraAwayScore": 0,
            "penHomeScore": 0,
            "penAwayScore": 0,
            "twoRoundsHomeScore": 0,
            "twoRoundsAwayScore": 0,
            "winner": 0
        },
        "hasLineup": false,
        "neutral": false,
        "injuryTime": 0,
        "var": "",
        "updateTime": 1761054359
    },
    {
        "matchId": "397067829",
        "leagueType": 2,
        "leagueId": "29650",
        "leagueName": "FYR Macedonia Cup",
        "leagueShortName": "MKD CUP",
        "leagueColor": "#cc9900",
        "subLeagueId": "",
        "subLeagueName": "",
        "matchTime": 1761048000,
        "halfStartTime": 1761051625,
        "status": -1,
        "homeId": "20356",
        "homeName": "FK Bashkimi",
        "awayId": "2383",
        "awayName": "Sileks",
        "homeScore": 1,
        "awayScore": 2,
        "homeHalfScore": 1,
        "awayHalfScore": 1,
        "homeRed": 0,
        "awayRed": 0,
        "homeYellow": 2,
        "awayYellow": 3,
        "homeCorner": 4,
        "awayCorner": 6,
        "homeRank": "MKD D1-5",
        "awayRank": "MKD D1-4",
        "season": "2025-2026",
        "stageId": "27276",
        "round": "Round 2",
        "group": "",
        "location": "",
        "weather": "Cloudy",
        "temperature": "17°C",
        "explain": "",
        "extraExplain": {
            "kickOff": 0,
            "minute": 0,
            "homeScore": 0,
            "awayScore": 0,
            "extraTimeStatus": 0,
            "extraHomeScore": 0,
            "extraAwayScore": 0,
            "penHomeScore": 0,
            "penAwayScore": 0,
            "twoRoundsHomeScore": 0,
            "twoRoundsAwayScore": 0,
            "winner": 0
        },
        "hasLineup": false,
        "neutral": false,
        "injuryTime": 0,
        "var": "",
        "updateTime": 1761054579
    },
    {
        "matchId": "368067827",
        "leagueType": 2,
        "leagueId": "29650",
        "leagueName": "FYR Macedonia Cup",
        "leagueShortName": "MKD CUP",
        "leagueColor": "#cc9900",
        "subLeagueId": "",
        "subLeagueName": "",
        "matchTime": 1761134400,
        "halfStartTime": 1761138227,
        "status": -1,
        "homeId": "940",
        "homeName": "FC Vardar Skopje",
        "awayId": "15349",
        "awayName": "FK Novaci",
        "homeScore": 3,
        "awayScore": 1,
        "homeHalfScore": 2,
        "awayHalfScore": 1,
        "homeRed": 0,
        "awayRed": 0,
        "homeYellow": 1,
        "awayYellow": 0,
        "homeCorner": 10,
        "awayCorner": 0,
        "homeRank": "MKD D1-2",
        "awayRank": "MKD D2-9",
        "season": "2025-2026",
        "stageId": "27276",
        "round": "Round 2",
        "group": "",
        "location": "National Arena Toshe Proeski",
        "weather": "Cloudy",
        "temperature": "16°C",
        "explain": "",
        "extraExplain": {
            "kickOff": 0,
            "minute": 0,
            "homeScore": 0,
            "awayScore": 0,
            "extraTimeStatus": 0,
            "extraHomeScore": 0,
            "extraAwayScore": 0,
            "penHomeScore": 0,
            "penAwayScore": 0,
            "twoRoundsHomeScore": 0,
            "twoRoundsAwayScore": 0,
            "winner": 0
        },
        "hasLineup": false,
        "neutral": false,
        "injuryTime": 0,
        "var": "",
        "updateTime": 1761177612
    },
    {
        "matchId": "358067826",
        "leagueType": 2,
        "leagueId": "29650",
        "leagueName": "FYR Macedonia Cup",
        "leagueShortName": "MKD CUP",
        "leagueColor": "#cc9900",
        "subLeagueId": "",
        "subLeagueName": "",
        "matchTime": 1763553600,
        "halfStartTime": 1763557222,
        "status": -1,
        "homeId": "4827",
        "homeName": "FK Shkendija 79",
        "awayId": "15344",
        "awayName": "FK Tikves Kavadarci",
        "homeScore": 2,
        "awayScore": 0,
        "homeHalfScore": 1,
        "awayHalfScore": 0,
        "homeRed": 0,
        "awayRed": 0,
        "homeYellow": 2,
        "awayYellow": 4,
        "homeCorner": 9,
        "awayCorner": 7,
        "homeRank": "MKD D1-3",
        "awayRank": "MKD D1-9",
        "season": "2025-2026",
        "stageId": "27276",
        "round": "Round 2",
        "group": "",
        "location": "Ecolog Arena",
        "weather": "Cloudy",
        "temperature": "12°C",
        "explain": "",
        "extraExplain": {
            "kickOff": 0,
            "minute": 0,
            "homeScore": 0,
            "awayScore": 0,
            "extraTimeStatus": 0,
            "extraHomeScore": 0,
            "extraAwayScore": 0,
            "penHomeScore": 0,
            "penAwayScore": 0,
            "twoRoundsHomeScore": 0,
            "twoRoundsAwayScore": 0,
            "winner": 0
        },
        "hasLineup": false,
        "neutral": false,
        "injuryTime": 0,
        "var": "",
        "updateTime": 1763596809
    },
    {
        "matchId": "485792922",
        "leagueType": 2,
        "leagueId": "29650",
        "leagueName": "FYR Macedonia Cup",
        "leagueShortName": "MKD CUP",
        "leagueColor": "#cc9900",
        "subLeagueId": "",
        "subLeagueName": "",
        "matchTime": 1771938000,
        "halfStartTime": 0,
        "status": -1,
        "homeId": "71510",
        "homeName": "Shkendija Haracine",
        "awayId": "2557",
        "awayName": "Rabotnicki Skopje",
        "homeScore": 3,
        "awayScore": 1,
        "homeHalfScore": 1,
        "awayHalfScore": 0,
        "homeRed": 0,
        "awayRed": 1,
        "homeYellow": 0,
        "awayYellow": 0,
        "homeCorner": 0,
        "awayCorner": 0,
        "homeRank": "MKD D2-2",
        "awayRank": "MKD D1-11",
        "season": "2025-2026",
        "stageId": "28151",
        "round": "Quarterfinals",
        "group": "",
        "location": "",
        "weather": "Cloudy",
        "temperature": "11°C",
        "explain": "",
        "extraExplain": {
            "kickOff": 0,
            "minute": 0,
            "homeScore": 0,
            "awayScore": 0,
            "extraTimeStatus": 0,
            "extraHomeScore": 0,
            "extraAwayScore": 0,
            "penHomeScore": 0,
            "penAwayScore": 0,
            "twoRoundsHomeScore": 0,
            "twoRoundsAwayScore": 0,
            "winner": 0
        },
        "hasLineup": false,
        "neutral": false,
        "injuryTime": 0,
        "var": "",
        "updateTime": 1771977608
    },
    {
        "matchId": "306792925",
        "leagueType": 2,
        "leagueId": "29650",
        "leagueName": "FYR Macedonia Cup",
        "leagueShortName": "MKD CUP",
        "leagueColor": "#cc9900",
        "subLeagueId": "",
        "subLeagueName": "",
        "matchTime": 1771938000,
        "halfStartTime": 1771941804,
        "status": -1,
        "homeId": "940",
        "homeName": "FC Vardar Skopje",
        "awayId": "15340",
        "awayName": "FK Ohrid 2004",
        "homeScore": 1,
        "awayScore": 1,
        "homeHalfScore": 0,
        "awayHalfScore": 0,
        "homeRed": 0,
        "awayRed": 1,
        "homeYellow": 0,
        "awayYellow": 4,
        "homeCorner": 8,
        "awayCorner": 1,
        "homeRank": "MKD D1-1",
        "awayRank": "MKD D2-1",
        "season": "2025-2026",
        "stageId": "28151",
        "round": "Quarterfinals",
        "group": "",
        "location": "National Arena Toshe Proeski",
        "weather": "Cloudy",
        "temperature": "13°C",
        "explain": "",
        "extraExplain": {
            "kickOff": 0,
            "minute": 90,
            "homeScore": 1,
            "awayScore": 1,
            "extraTimeStatus": 0,
            "extraHomeScore": 0,
            "extraAwayScore": 0,
            "penHomeScore": 2,
            "penAwayScore": 4,
            "twoRoundsHomeScore": 0,
            "twoRoundsAwayScore": 0,
            "winner": 2
        },
        "hasLineup": false,
        "neutral": false,
        "injuryTime": 0,
        "var": "",
        "updateTime": 1771977608
    },
    {
        "matchId": "475792921",
        "leagueType": 2,
        "leagueId": "29650",
        "leagueName": "FYR Macedonia Cup",
        "leagueShortName": "MKD CUP",
        "leagueColor": "#cc9900",
        "subLeagueId": "",
        "subLeagueName": "",
        "matchTime": 1772024400,
        "halfStartTime": 0,
        "status": -1,
        "homeId": "63039",
        "homeName": "Detonit Plachkovica",
        "awayId": "2383",
        "awayName": "Sileks",
        "homeScore": 0,
        "awayScore": 3,
        "homeHalfScore": 0,
        "awayHalfScore": 1,
        "homeRed": 0,
        "awayRed": 0,
        "homeYellow": 3,
        "awayYellow": 2,
        "homeCorner": 2,
        "awayCorner": 1,
        "homeRank": "MKD D2-9",
        "awayRank": "MKD D1-4",
        "season": "2025-2026",
        "stageId": "28151",
        "round": "Quarterfinals",
        "group": "",
        "location": "",
        "weather": "Few Cloudy",
        "temperature": "9°C",
        "explain": "",
        "extraExplain": {
            "kickOff": 0,
            "minute": 0,
            "homeScore": 0,
            "awayScore": 0,
            "extraTimeStatus": 0,
            "extraHomeScore": 0,
            "extraAwayScore": 0,
            "penHomeScore": 0,
            "penAwayScore": 0,
            "twoRoundsHomeScore": 0,
            "twoRoundsAwayScore": 0,
            "winner": 0
        },
        "hasLineup": false,
        "neutral": false,
        "injuryTime": 0,
        "var": "",
        "updateTime": 1772064008
    },
    {
        "matchId": "495792923",
        "leagueType": 2,
        "leagueId": "29650",
        "leagueName": "FYR Macedonia Cup",
        "leagueShortName": "MKD CUP",
        "leagueColor": "#cc9900",
        "subLeagueId": "",
        "subLeagueName": "",
        "matchTime": 1773840600,
        "halfStartTime": 1773844252,
        "status": -1,
        "homeId": "33778",
        "homeName": "FC Struga Trim Lum",
        "awayId": "4827",
        "awayName": "FK Shkendija 79",
        "homeScore": 2,
        "awayScore": 2,
        "homeHalfScore": 1,
        "awayHalfScore": 0,
        "homeRed": 0,
        "awayRed": 0,
        "homeYellow": 2,
        "awayYellow": 4,
        "homeCorner": 4,
        "awayCorner": 6,
        "homeRank": "MKD D1-3",
        "awayRank": "MKD D1-2",
        "season": "2025-2026",
        "stageId": "28151",
        "round": "Quarterfinals",
        "group": "",
        "location": "",
        "weather": "Cloudy",
        "temperature": "9°C",
        "explain": "",
        "extraExplain": {
            "kickOff": 0,
            "minute": 90,
            "homeScore": 2,
            "awayScore": 2,
            "extraTimeStatus": 0,
            "extraHomeScore": 0,
            "extraAwayScore": 0,
            "penHomeScore": 4,
            "penAwayScore": 5,
            "twoRoundsHomeScore": 0,
            "twoRoundsAwayScore": 0,
            "winner": 2
        },
        "hasLineup": false,
        "neutral": false,
        "injuryTime": 0,
        "var": "",
        "updateTime": 1773848172
    },
    {
        "matchId": "419985923",
        "leagueType": 2,
        "leagueId": "29650",
        "leagueName": "FYR Macedonia Cup",
        "leagueShortName": "MKD CUP",
        "leagueColor": "#cc9900",
        "subLeagueId": "",
        "subLeagueName": "",
        "matchTime": 1776852000,
        "halfStartTime": 1776855720,
        "status": -1,
        "homeId": "15340",
        "homeName": "FK Ohrid 2004",
        "awayId": "2383",
        "awayName": "Sileks",
        "homeScore": 1,
        "awayScore": 1,
        "homeHalfScore": 1,
        "awayHalfScore": 1,
        "homeRed": 0,
        "awayRed": 0,
        "homeYellow": 8,
        "awayYellow": 1,
        "homeCorner": 1,
        "awayCorner": 2,
        "homeRank": "MKD D2-2",
        "awayRank": "MKD D1-4",
        "season": "2025-2026",
        "stageId": "28152",
        "round": "Semifinal",
        "group": "",
        "location": "",
        "weather": "Cloudy",
        "temperature": "11°C",
        "explain": "",
        "extraExplain": {
            "kickOff": 0,
            "minute": 0,
            "homeScore": 0,
            "awayScore": 0,
            "extraTimeStatus": 1,
            "extraHomeScore": 0,
            "extraAwayScore": 0,
            "penHomeScore": 0,
            "penAwayScore": 0,
            "twoRoundsHomeScore": 0,
            "twoRoundsAwayScore": 0,
            "winner": 0
        },
        "hasLineup": false,
        "neutral": false,
        "injuryTime": 0,
        "var": "",
        "updateTime": 1776865739
    },
    {
        "matchId": "352746925",
        "leagueType": 2,
        "leagueId": "29650",
        "leagueName": "FYR Macedonia Cup",
        "leagueShortName": "MKD CUP",
        "leagueColor": "#cc9900",
        "subLeagueId": "",
        "subLeagueName": "",
        "matchTime": 1776859200,
        "halfStartTime": 1776862950,
        "status": -1,
        "homeId": "4827",
        "homeName": "FK Shkendija 79",
        "awayId": "71510",
        "awayName": "Shkendija Haracine",
        "homeScore": 3,
        "awayScore": 2,
        "homeHalfScore": 1,
        "awayHalfScore": 2,
        "homeRed": 0,
        "awayRed": 0,
        "homeYellow": 3,
        "awayYellow": 1,
        "homeCorner": 8,
        "awayCorner": 1,
        "homeRank": "MKD D1-2",
        "awayRank": "MKD D2-4",
        "season": "2025-2026",
        "stageId": "28152",
        "round": "Semifinal",
        "group": "",
        "location": "Ecolog Arena",
        "weather": "Cloudy",
        "temperature": "11°C",
        "explain": "",
        "extraExplain": {
            "kickOff": 0,
            "minute": 0,
            "homeScore": 0,
            "awayScore": 0,
            "extraTimeStatus": 0,
            "extraHomeScore": 0,
            "extraAwayScore": 0,
            "penHomeScore": 0,
            "penAwayScore": 0,
            "twoRoundsHomeScore": 0,
            "twoRoundsAwayScore": 0,
            "winner": 0
        },
        "hasLineup": false,
        "neutral": false,
        "injuryTime": 0,
        "var": "",
        "updateTime": 1776902410
    },
    {
        "matchId": "362746926",
        "leagueType": 2,
        "leagueId": "29650",
        "leagueName": "FYR Macedonia Cup",
        "leagueShortName": "MKD CUP",
        "leagueColor": "#cc9900",
        "subLeagueId": "",
        "subLeagueName": "",
        "matchTime": 1778076000,
        "halfStartTime": 0,
        "status": 0,
        "homeId": "71510",
        "homeName": "Shkendija Haracine",
        "awayId": "4827",
        "awayName": "FK Shkendija 79",
        "homeScore": 0,
        "awayScore": 0,
        "homeHalfScore": 0,
        "awayHalfScore": 0,
        "homeRed": 0,
        "awayRed": 0,
        "homeYellow": 0,
        "awayYellow": 0,
        "homeCorner": 0,
        "awayCorner": 0,
        "homeRank": "MKD D2-3",
        "awayRank": "MKD D1-2",
        "season": "2025-2026",
        "stageId": "28152",
        "round": "Semifinal",
        "group": "",
        "location": "",
        "weather": "Few Cloudy",
        "temperature": "27°C",
        "explain": "",
        "extraExplain": {
            "kickOff": 0,
            "minute": 0,
            "homeScore": 0,
            "awayScore": 0,
            "extraTimeStatus": 0,
            "extraHomeScore": 0,
            "extraAwayScore": 0,
            "penHomeScore": 0,
            "penAwayScore": 0,
            "twoRoundsHomeScore": 0,
            "twoRoundsAwayScore": 0,
            "winner": 0
        },
        "hasLineup": false,
        "neutral": false,
        "injuryTime": 0,
        "var": "",
        "updateTime": 1778058008
    },
    {
        "matchId": "429985924",
        "leagueType": 2,
        "leagueId": "29650",
        "leagueName": "FYR Macedonia Cup",
        "leagueShortName": "MKD CUP",
        "leagueColor": "#cc9900",
        "subLeagueId": "",
        "subLeagueName": "",
        "matchTime": 1778076000,
        "halfStartTime": 0,
        "status": 0,
        "homeId": "2383",
        "homeName": "Sileks",
        "awayId": "15340",
        "awayName": "FK Ohrid 2004",
        "homeScore": 0,
        "awayScore": 0,
        "homeHalfScore": 0,
        "awayHalfScore": 0,
        "homeRed": 0,
        "awayRed": 0,
        "homeYellow": 0,
        "awayYellow": 0,
        "homeCorner": 0,
        "awayCorner": 0,
        "homeRank": "MKD D1-4",
        "awayRank": "MKD D2-4",
        "season": "2025-2026",
        "stageId": "28152",
        "round": "Semifinal",
        "group": "",
        "location": "Sileks",
        "weather": "Clear",
        "temperature": "24°C",
        "explain": "",
        "extraExplain": {
            "kickOff": 0,
            "minute": 0,
            "homeScore": 0,
            "awayScore": 0,
            "extraTimeStatus": 0,
            "extraHomeScore": 0,
            "extraAwayScore": 0,
            "penHomeScore": 0,
            "penAwayScore": 0,
            "twoRoundsHomeScore": 0,
            "twoRoundsAwayScore": 0,
            "winner": 0
        },
        "hasLineup": false,
        "neutral": false,
        "injuryTime": 0,
        "var": "",
        "updateTime": 1778058008
    }
]
